Workbook

Sheet README
A1: RetailMart Bronze Layer — Data Quality Report
A3: Prepared for: Kajal — Bronze Layer Profiling → Silver Layer Cleaning Rules
A5: Scope: 7 source tables (customers, employees, stores, products, inventory, sales, returns), 69 individual data quality checks, each run against the raw bronze CSV extract.
A7: How this report is structured
A8: • 'Data Quality Report' tab — one row per (Table, Column, Check). Issue Count and Issue % are computed directly from the bronze CSVs; Issue % recalculates automatically if you edit Issue Count or Total Rows.
A9: • 'Summary' tab — issue counts rolled up by table and by severity, plus a chart.
A11: Severity definitions
A12: High — Breaks referential integrity, violates a hard business rule, or would corrupt a downstream KPI (e.g. cost > price, orphan foreign key, negative quantity, duplicate primary key). Silver layer should reject or quarantine these rows, not silently pass them through.
A13: Medium — Row is usable but needs standardization or a judgment call before it can be trusted in reporting (e.g. inconsistent date format, missing category, salary outlier). Silver layer transforms or flags these; does not typically reject the row outright.
A14: Low — Cosmetic / non-blocking inconsistency (e.g. casing, whitespace, missing non-critical field). Silver layer standardizes these as part of routine cleaning; does not require a data steward decision.
A16: Column definitions
A17: • Table — the bronze-layer source file the check was run against.
... A24: • Silver Action — the specific transformation, standardization, or rejection rule to apply when building the Silver layer.

Sheet RetailMart Data Quality Report
A1: Table | B1: Column | C1: Check | D1: Issue Count | E1: Total Rows | F1: Issue % | G1: Severity | H1: Silver Action
A2: customers | B2: customer_id | C2: Duplicate primary key
A3: customers | B3: email | C3: Missing value
A4: customers | B4: email | C4: Invalid format (missing @ / domain)
A5: customers | B5: phone_number | C5: Missing value
A6: customers | B6: phone_number | C6: Invalid length / inconsistent format
A7: customers | B7: gender | C7: Inconsistent categorical values
A8: customers | B8: date_of_birth | C8: Inconsistent date format
A9: customers | B9: date_of_birth | C9: Outlier — implausible age (<10 or >100)
A10: customers | B10: registration_date | C10: Inconsistent date format
A11: customers | B11: registration_date | C11: Future-dated value
A12: customers | B12: customer_status | C12: Inconsistent casing / whitespace
A13: customers | B13: customer_name | C13: Leading/trailing whitespace
... A70: returns | B70: return_status | C70: Inconsistent casing

Sheet Data Quality Report
A1: Table | B1: Column | C1: Check | D1: Issue Count | E1: Total Rows | F1: Issue % | G1: Severity | H1: Silver Action
A2: customers | B2: customer_id | C2: Duplicate primary key | D2: 450 | E2: 30450 | F2: =IF(E2=0,0,D2/E2) -> 0.014778325 | G2: High | H2: Deduplicate on customer_id, keep most recent registration_date, log removed rows to quarantine
A3: customers | B3: email | C3: Missing value | D3: 1218 | E3: 30450 | F3: =IF(E3=0,0,D3/E3) -> 0.04 | G3: Medium | H3: Flag NULL; do not block load, route to Customer Data Steward for backfill
A4: customers | B4: email | C4: Invalid format (missing @ / domain) | D4: 588 | E4: 30450 | F4: =IF(E4=0,0,D4/E4) -> 0.019310345 | G4: Medium | H4: Reject malformed emails to quarantine table; do not attempt auto-correction
A5: customers | B5: phone_number | C5: Missing value | D5: 913 | E5: 30450 | F5: =IF(E5=0,0,D5/E5) -> 0.02998358 | G5: Low | H5: Flag NULL, allow load (non-critical for core sales KPIs)
A6: customers | B6: phone_number | C6: Invalid length / inconsistent format | D6: 4199 | E6: 30450 | F6: =IF(E6=0,0,D6/E6) -> 0.13789819 | G6: Medium | H6: Strip non-numeric characters, standardize to 10-digit numeric string; quarantine if still invalid
A7: customers | B7: gender | C7: Inconsistent categorical values | D7: 3432 | E7: 30450 | F7: =IF(E7=0,0,D7/E7) -> 0.11270936 | G7: Low | H7: Standardize via mapping table (trim, upper-case compare) to Male / Female / Other
A8: customers | B8: date_of_birth | C8: Inconsistent date format | D8: 6057 | E8: 30450 | F8: =IF(E8=0,0,D8/E8) -> 0.19891626 | G8: Medium | H8: Standardize all date formats to YYYY-MM-DD using multi-format parser; quarantine unparseable values
A9: customers | B9: date_of_birth | C9: Outlier — implausible age (<10 or >100) | D9: 182 | E9: 30450 | F9: =IF(E9=0,0,D9/E9) -> 0.0059770115 | G9: High | H9: Flag for manual review; exclude from active-customer KPIs until corrected
A10: customers | B10: registration_date | C10: Inconsistent date format | D10: 4550 | E10: 30450 | F10: =IF(E10=0,0,D10/E10) -> 0.14942529 | G10: Medium | H10: Standardize to YYYY-MM-DD using multi-format parser
A11: customers | B11: registration_date | C11: Future-dated value | D11: 152 | E11: 30450 | F11: =IF(E11=0,0,D11/E11) -> 0.0049917898 | G11: High | H11: Reject rows with registration_date > current load date; route to exception queue
A12: customers | B12: customer_status | C12: Inconsistent casing / whitespace | D12: 2436 | E12: 30450 | F12: =IF(E12=0,0,D12/E12) -> 0.08 | G12: Low | H12: Trim whitespace, standardize casing (Title Case) via mapping table
A13: customers | B13: customer_name | C13: Leading/trailing whitespace | D13: 744 | E13: 30450 | F13: =IF(E13=0,0,D13/E13) -> 0.024433498 | G13: Low | H13: Trim whitespace; standardize to Title Case
... A70: returns | B70: return_status | C70: Inconsistent casing | D70: 1818 | E70: 30300 | F70: =IF(E70=0,0,D70/E70) -> 0.06 | G70: Low | H70: Trim, standardize casing via mapping table

Sheet Summary
A1: Data Quality Summary — by Table
A3: Table | B3: Total Checks | C3: High | D3: Medium | E3: Low | F3: Total Issue Rows Flagged
A4: customers | B4: =COUNTIF('Data Quality Report'!A:A,A4) -> 15 | C4: =COUNTIFS('Data Quality Report'!A:A,A4,'Data Quality Report'!G:G,"High") -> 3 | D4: =COUNTIFS('Data Quality Report'!A:A,A4,'Data Quality Report'!G:G,"Medium") -> 5 | E4: =COUNTIFS('Data Quality Report'!A:A,A4,'Data Quality Report'!G:G,"Low") -> 7 | F4: =SUMIF('Data Quality Report'!A:A,A4,'Data Quality Report'!D:D) -> 26495
A5: employees | B5: =COUNTIF('Data Quality Report'!A:A,A5) -> 10 | C5: =COUNTIFS('Data Quality Report'!A:A,A5,'Data Quality Report'!G:G,"High") -> 3 | D5: =COUNTIFS('Data Quality Report'!A:A,A5,'Data Quality Report'!G:G,"Medium") -> 3 | E5: =COUNTIFS('Data Quality Report'!A:A,A5,'Data Quality Report'!G:G,"Low") -> 4 | F5: =SUMIF('Data Quality Report'!A:A,A5,'Data Quality Report'!D:D) -> 11267
A6: stores | B6: =COUNTIF('Data Quality Report'!A:A,A6) -> 6 | C6: =COUNTIFS('Data Quality Report'!A:A,A6,'Data Quality Report'!G:G,"High") -> 1 | D6: =COUNTIFS('Data Quality Report'!A:A,A6,'Data Quality Report'!G:G,"Medium") -> 2 | E6: =COUNTIFS('Data Quality Report'!A:A,A6,'Data Quality Report'!G:G,"Low") -> 3 | F6: =SUMIF('Data Quality Report'!A:A,A6,'Data Quality Report'!D:D) -> 8495
A7: products | B7: =COUNTIF('Data Quality Report'!A:A,A7) -> 8 | C7: =COUNTIFS('Data Quality Report'!A:A,A7,'Data Quality Report'!G:G,"High") -> 3 | D7: =COUNTIFS('Data Quality Report'!A:A,A7,'Data Quality Report'!G:G,"Medium") -> 1 | E7: =COUNTIFS('Data Quality Report'!A:A,A7,'Data Quality Report'!G:G,"Low") -> 4 | F7: =SUMIF('Data Quality Report'!A:A,A7,'Data Quality Report'!D:D) -> 10407
A8: inventory | B8: =COUNTIF('Data Quality Report'!A:A,A8) -> 9 | C8: =COUNTIFS('Data Quality Report'!A:A,A8,'Data Quality Report'!G:G,"High") -> 6 | D8: =COUNTIFS('Data Quality Report'!A:A,A8,'Data Quality Report'!G:G,"Medium") -> 1 | E8: =COUNTIFS('Data Quality Report'!A:A,A8,'Data Quality Report'!G:G,"Low") -> 2 | F8: =SUMIF('Data Quality Report'!A:A,A8,'Data Quality Report'!D:D) -> 29532
A9: sales | B9: =COUNTIF('Data Quality Report'!A:A,A9) -> 12 | C9: =COUNTIFS('Data Quality Report'!A:A,A9,'Data Quality Report'!G:G,"High") -> 8 | D9: =COUNTIFS('Data Quality Report'!A:A,A9,'Data Quality Report'!G:G,"Medium") -> 3 | E9: =COUNTIFS('Data Quality Report'!A:A,A9,'Data Quality Report'!G:G,"Low") -> 1 | F9: =SUMIF('Data Quality Report'!A:A,A9,'Data Quality Report'!D:D) -> 37638
A10: returns | B10: =COUNTIF('Data Quality Report'!A:A,A10) -> 9 | C10: =COUNTIFS('Data Quality Report'!A:A,A10,'Data Quality Report'!G:G,"High") -> 6 | D10: =COUNTIFS('Data Quality Report'!A:A,A10,'Data Quality Report'!G:G,"Medium") -> 1 | E10: =COUNTIFS('Data Quality Report'!A:A,A10,'Data Quality Report'!G:G,"Low") -> 2 | F10: =SUMIF('Data Quality Report'!A:A,A10,'Data Quality Report'!D:D) -> 10187
A11: TOTAL | B11: =SUM(B4:B10) -> 69 | C11: =SUM(C4:C10) -> 30 | D11: =SUM(D4:D10) -> 16 | E11: =SUM(E4:E10) -> 23 | F11: =SUM(F4:F10) -> 134021
A33: Overall Severity Mix
